klumpy/Classes.py
klumpy/__init__.py
klumpy/__main__.py
klumpy/alignment_plot.py
klumpy/combine_klumps.py
klumpy/find_gaps.py
klumpy/find_klumps.py
klumpy/get_exons.py
klumpy/grouping.py
klumpy/klump_plot.py
klumpy/klump_sizes.py
klumpy/kmerize.py
klumpy/scan_alignments.py
klumpy-1.1.1.data/scripts/klumpy
klumpy-1.1.1.dist-info/LICENSE
klumpy-1.1.1.dist-info/METADATA
klumpy-1.1.1.dist-info/WHEEL
klumpy-1.1.1.dist-info/top_level.txt
klumpy-1.1.1.dist-info/RECORD
