Metadata-Version: 2.1
Name: klumpy
Version: 1.1.1
Summary: A package to evaluate genome assemblies and detect sequence motifs
Author: Giovanni Madrigal <gm33@illinois.edu>, Bushra Fazal Minhas <bfazal2@illinois.edu>, Julian Catchen <jcatchen@illinois.edu>
Author-email: gm33@illinois.edu
Classifier: Programming Language :: Python :: 3
Classifier: Operating System :: POSIX
Classifier: License :: OSI Approved :: GNU General Public License v3 (GPLv3)
Requires-Python: >=3.6.0
License-File: LICENSE
Requires-Dist: pycairo
